imuthes/alchemy/.git
imuthes/alchemy/README.md
imuthes/alchemy/__init__.py
imuthes/alchemy/classes.puml
imuthes/alchemy/engine/__init__.py
imuthes/alchemy/engine/engine.py
imuthes/alchemy/exceptions/__init__.py
imuthes/alchemy/exceptions/alchemy_exception.py
imuthes/alchemy/exceptions/class_not_found_error.py
imuthes/alchemy/exceptions/dependents_found_error.py
imuthes/alchemy/exceptions/multiple_records_found_error.py
imuthes/alchemy/exceptions/name_length_exceeded_error.py
imuthes/alchemy/exceptions/record_not_found_error.py
imuthes/alchemy/exceptions/record_not_selectable_error.py
imuthes/alchemy/util.py
imuthes/alchemy/versions/__init__.py
imuthes/alchemy/versions/versioned.py
imuthes_alchemy-0.1.0.dist-info/METADATA
imuthes_alchemy-0.1.0.dist-info/WHEEL
imuthes_alchemy-0.1.0.dist-info/RECORD
