Metadata-Version: 2.3
Name: imuthes-alchemy
Version: 0.1.0
Summary: SQL Alchemy related utilities
License: LGPL-3.0-or-later
Keywords: tools
Author: Bernhard Radermacher
Author-email: bernhard.radermacher@netlink-consulting.com
Requires-Python: >=3.11,<4.0
Classifier: Development Status :: 3 - Alpha
Classifier: Intended Audience :: Developers
Classifier: License :: OSI Approved :: GNU Lesser General Public License v3 or later (LGPLv3+)
Classifier: Programming Language :: Python :: 3.11
Classifier: Programming Language :: Python :: 3.12
Classifier: Programming Language :: Python :: 3.13
Classifier: Topic :: Software Development
Classifier: Topic :: Utilities
Classifier: Typing :: Typed
Requires-Dist: setuptools (>=78.1.0,<79.0.0)
Requires-Dist: sqlalchemy-history (>=2.1.4,<3.0.0)
Project-URL: Repository, https://gitlab.com/imuthes-py/imuthes-alchemy
